litresapi/__init__.py
litresapi/core.py
litresapi/exceptions.py
litresapi/xmltodict.py
litresapi-1.0.1.dist-info/top_level.txt
litresapi-1.0.1.dist-info/METADATA
litresapi-1.0.1.dist-info/DESCRIPTION.rst
litresapi-1.0.1.dist-info/metadata.json
litresapi-1.0.1.dist-info/WHEEL
litresapi-1.0.1.dist-info/RECORD
