Metadata-Version: 2.0
Name: litresapi
Version: 1.0.1
Summary: Litres API
Home-page: https://github.com/MyBook/litresapi
Author: MyBook
Author-email: dev@mybook.ru
License: BSD
Keywords: litresapi
Platform: UNKNOWN
Classifier: Development Status :: 5 - Production/Stable
Classifier: Intended Audience :: Developers
Classifier: License :: OSI Approved :: BSD License
Classifier: Natural Language :: English
Classifier: Programming Language :: Python :: 2
Classifier: Programming Language :: Python :: 2.7
Classifier: Programming Language :: Python :: 3
Classifier: Programming Language :: Python :: 3.4
Classifier: Programming Language :: Python :: 3.5
Requires-Dist: requests (>=2.7.0)
Requires-Dist: lxml (>=3.4.4)
